swagger_schema/__init__.py
swagger_schema/contact.py
swagger_schema/external_documentation.py
swagger_schema/headers.py
swagger_schema/info.py
swagger_schema/items.py
swagger_schema/license.py
swagger_schema/operation.py
swagger_schema/parameter.py
swagger_schema/path_item.py
swagger_schema/reference.py
swagger_schema/response.py
swagger_schema/schema.py
swagger_schema/swagger.py
swagger_schema/tag.py
swagger_schema/types.py
swagger_schema/tests/__init__.py
swagger_schema/tests/conftest.py
swagger_schema/tests/test_contact.py
swagger_schema/tests/test_external_documentation.py
swagger_schema/tests/test_full_example.py
swagger_schema/tests/test_info.py
swagger_schema/tests/test_items.py
swagger_schema/tests/test_license.py
swagger_schema/tests/test_parameter.py
swagger_schema/tests/test_response.py
swagger_schema/tests/test_schema.py
swagger_schema/tests/test_swagger.py
swagger_schema/tests/test_types.py
swagger_schema-0.5.1.dist-info/DESCRIPTION.rst
swagger_schema-0.5.1.dist-info/METADATA
swagger_schema-0.5.1.dist-info/RECORD
swagger_schema-0.5.1.dist-info/WHEEL
swagger_schema-0.5.1.dist-info/metadata.json
swagger_schema-0.5.1.dist-info/top_level.txt
